femtosphinx/ENV_REQUIREMENTS.sh
femtosphinx/PY_REQUIREMENTS
femtosphinx/VERSION
femtosphinx/__init__.py
femtosphinx/execute_code.py
femtosphinx/foo.py
femtosphinx-0.1.4.dev0.dist-info/LICENSE
femtosphinx-0.1.4.dev0.dist-info/METADATA
femtosphinx-0.1.4.dev0.dist-info/WHEEL
femtosphinx-0.1.4.dev0.dist-info/top_level.txt
femtosphinx-0.1.4.dev0.dist-info/RECORD
