Metadata-Version: 2.1
Name: femtosphinx
Version: 0.1.4.dev0
Summary: template project/walkthrough
Home-page: https://github.com/femtosense/femtosphinx
Author: Femtosense
Author-email: info@femtosense.ai
License: UNKNOWN
Project-URL: Source, https://github.com/femtosense/femtosphinx
Platform: UNKNOWN
Classifier: Development Status :: 3 - Alpha
Classifier: Intended Audience :: Developers
Classifier: Programming Language :: Python :: 3.6
Classifier: Programming Language :: Python :: 3.7
Classifier: Programming Language :: Python :: 3.8
Classifier: Programming Language :: Python :: 3 :: Only
Classifier: Operating System :: OS Independent
Requires-Python: >=3.6
License-File: LICENSE
